searchep/GPFlow_model_class.py
searchep/__init__.py
searchep/data.py
searchep/eval.py
searchep/gpr.py
searchep/main.py
searchep/matrix.py
searchep/plots.py
searchep/tests.py
searchep/training.py
searchep/zero_search.py
searchep-0.1.3.dist-info/LICENSE
searchep-0.1.3.dist-info/METADATA
searchep-0.1.3.dist-info/WHEEL
searchep-0.1.3.dist-info/RECORD
